dfhelp/__init__.py
dfhelp/exception.py
dfhelp/io.py
dfhelp/main.py
dfhelp/schema.py
dfhelp/typing.py
dfhelp-0.0.3.dist-info/METADATA
dfhelp-0.0.3.dist-info/WHEEL
dfhelp-0.0.3.dist-info/top_level.txt
dfhelp-0.0.3.dist-info/RECORD
