Metadata-Version: 2.4
Name: DFHelp
Version: 0.0.3
Requires-Python: >=3.10
Requires-Dist: pandas<3,>=2
Requires-Dist: polars<2,>=1
Requires-Dist: pyarrow
